{
  "_meta": {
    "lastUpdated": "2026-03-20",
    "source": "gemini_news (Gemini 2.5 Flash + 토속언론)",
    "region": "gyeongbuk"
  },
  "candidates": {
    "포항시가선거구": [
      {
        "name": "김종익",
        "party": "ppp",
        "career": "",
        "status": "EXPECTED",
        "dataSource": "incumbent",
        "isIncumbent": true,
        "_seats": 2,
        "pledges": []
      },
      {
        "name": "백강훈",
        "party": "ppp",
        "career": "",
        "status": "EXPECTED",
        "dataSource": "incumbent",
        "isIncumbent": true,
        "_seats": 2,
        "pledges": []
      }
    ],
    "포항시나선거구": [
      {
        "name": "이상범",
        "party": "ppp",
        "career": "",
        "status": "EXPECTED",
        "dataSource": "incumbent",
        "isIncumbent": true,
        "_seats": 2,
        "pledges": []
      },
      {
        "name": "강필순",
        "party": "independent",
        "career": "",
        "status": "EXPECTED",
        "dataSource": "incumbent",
        "isIncumbent": true,
        "_seats": 2,
        "pledges": []
      }
    ],
    "포항시다선거구": [
      {
        "name": "황찬규",
        "party": "ppp",
        "career": "",
        "status": "EXPECTED",
        "dataSource": "incumbent",
        "isIncumbent": true,
        "_seats": 3,
        "pledges": []
      },
      {
        "name": "김만호",
        "party": "democratic",
        "career": "",
        "status": "EXPECTED",
        "dataSource": "incumbent",
        "isIncumbent": true,
        "_seats": 3,
        "pledges": []
      },
      {
        "name": "김일만",
        "party": "ppp",
        "career": "",
        "status": "EXPECTED",
        "dataSource": "incumbent",
        "isIncumbent": true,
        "_seats": 3,
        "pledges": []
      }
    ],
    "포항시라선거구": [
      {
        "name": "김상일",
        "party": "ppp",
        "career": "",
        "status": "EXPECTED",
        "dataSource": "incumbent",
        "isIncumbent": true,
        "_seats": 3,
        "pledges": []
      },
      {
        "name": "전주형",
        "party": "democratic",
        "career": "",
        "status": "EXPECTED",
        "dataSource": "incumbent",
        "isIncumbent": true,
        "_seats": 3,
        "pledges": []
      },
      {
        "name": "안병국",
        "party": "ppp",
        "career": "",
        "status": "EXPECTED",
        "dataSource": "incumbent",
        "isIncumbent": true,
        "_seats": 3,
        "pledges": []
      }
    ],
    "포항시마선거구": [
      {
        "name": "정원석",
        "party": "ppp",
        "career": "",
        "status": "EXPECTED",
        "dataSource": "incumbent",
        "isIncumbent": true,
        "_seats": 3,
        "pledges": []
      },
      {
        "name": "배상신",
        "party": "ppp",
        "career": "",
        "status": "EXPECTED",
        "dataSource": "incumbent",
        "isIncumbent": true,
        "_seats": 3,
        "pledges": []
      },
      {
        "name": "김상민",
        "party": "democratic",
        "career": "",
        "status": "EXPECTED",
        "dataSource": "incumbent",
        "isIncumbent": true,
        "_seats": 3,
        "pledges": []
      }
    ],
    "포항시바선거구": [
      {
        "name": "김성조",
        "party": "independent",
        "career": "",
        "status": "EXPECTED",
        "dataSource": "incumbent",
        "isIncumbent": true,
        "_seats": 2,
        "pledges": []
      },
      {
        "name": "김민정",
        "party": "ppp",
        "career": "",
        "status": "EXPECTED",
        "dataSource": "incumbent",
        "isIncumbent": true,
        "_seats": 2,
        "pledges": []
      }
    ],
    "포항시사선거구": [
      {
        "name": "양윤제",
        "party": "ppp",
        "career": "",
        "status": "EXPECTED",
        "dataSource": "incumbent",
        "isIncumbent": true,
        "_seats": 3,
        "pledges": []
      },
      {
        "name": "조민성",
        "party": "ppp",
        "career": "",
        "status": "EXPECTED",
        "dataSource": "incumbent",
        "isIncumbent": true,
        "_seats": 3,
        "pledges": []
      },
      {
        "name": "조영원",
        "party": "independent",
        "career": "",
        "status": "EXPECTED",
        "dataSource": "incumbent",
        "isIncumbent": true,
        "_seats": 3,
        "pledges": []
      }
    ],
    "포항시아선거구": [
      {
        "name": "김영헌",
        "party": "ppp",
        "career": "",
        "status": "EXPECTED",
        "dataSource": "incumbent",
        "isIncumbent": true,
        "_seats": 2,
        "pledges": []
      },
      {
        "name": "김철수",
        "party": "independent",
        "career": "",
        "status": "EXPECTED",
        "dataSource": "incumbent",
        "isIncumbent": true,
        "_seats": 2,
        "pledges": []
      }
    ],
    "포항시자선거구": [
      {
        "name": "최해곤",
        "party": "ppp",
        "career": "",
        "status": "EXPECTED",
        "dataSource": "incumbent",
        "isIncumbent": true,
        "_seats": 3,
        "pledges": []
      },
      {
        "name": "최광열",
        "party": "democratic",
        "career": "",
        "status": "EXPECTED",
        "dataSource": "incumbent",
        "isIncumbent": true,
        "_seats": 3,
        "pledges": []
      },
      {
        "name": "방진길",
        "party": "ppp",
        "career": "",
        "status": "EXPECTED",
        "dataSource": "incumbent",
        "isIncumbent": true,
        "_seats": 3,
        "pledges": []
      }
    ],
    "포항시차선거구": [
      {
        "name": "임주희",
        "party": "ppp",
        "career": "",
        "status": "EXPECTED",
        "dataSource": "incumbent",
        "isIncumbent": true,
        "_seats": 3,
        "pledges": []
      },
      {
        "name": "박칠용",
        "party": "democratic",
        "career": "",
        "status": "EXPECTED",
        "dataSource": "incumbent",
        "isIncumbent": true,
        "_seats": 3,
        "pledges": []
      },
      {
        "name": "함정호",
        "party": "ppp",
        "career": "",
        "status": "EXPECTED",
        "dataSource": "incumbent",
        "isIncumbent": true,
        "_seats": 3,
        "pledges": []
      }
    ],
    "포항시카선거구": [
      {
        "name": "이재진",
        "party": "ppp",
        "career": "",
        "status": "EXPECTED",
        "dataSource": "incumbent",
        "isIncumbent": true,
        "_seats": 3,
        "pledges": []
      },
      {
        "name": "김형철",
        "party": "ppp",
        "career": "",
        "status": "EXPECTED",
        "dataSource": "incumbent",
        "isIncumbent": true,
        "_seats": 3,
        "pledges": []
      },
      {
        "name": "박희정",
        "party": "democratic",
        "career": "",
        "status": "EXPECTED",
        "dataSource": "incumbent",
        "isIncumbent": true,
        "_seats": 3,
        "pledges": []
      }
    ],
    "울릉군가선거구": [
      {
        "name": "홍성근",
        "party": "ppp",
        "career": "",
        "status": "EXPECTED",
        "dataSource": "incumbent",
        "isIncumbent": true,
        "_seats": 4,
        "pledges": []
      },
      {
        "name": "정인식",
        "party": "independent",
        "career": "",
        "status": "EXPECTED",
        "dataSource": "incumbent",
        "isIncumbent": true,
        "_seats": 4,
        "pledges": []
      },
      {
        "name": "공경식",
        "party": "independent",
        "career": "",
        "status": "EXPECTED",
        "dataSource": "incumbent",
        "isIncumbent": true,
        "_seats": 4,
        "pledges": []
      },
      {
        "name": "최경환",
        "party": "ppp",
        "career": "",
        "status": "EXPECTED",
        "dataSource": "incumbent",
        "isIncumbent": true,
        "_seats": 4,
        "pledges": []
      }
    ],
    "울릉군나선거구": [
      {
        "name": "최병호",
        "party": "independent",
        "career": "",
        "status": "EXPECTED",
        "dataSource": "incumbent",
        "isIncumbent": true,
        "_seats": 2,
        "pledges": []
      },
      {
        "name": "이상식",
        "party": "ppp",
        "career": "",
        "status": "EXPECTED",
        "dataSource": "incumbent",
        "isIncumbent": true,
        "_seats": 2,
        "pledges": []
      }
    ],
    "경주시가선거구": [
      {
        "name": "이경희",
        "party": "ppp",
        "career": "",
        "status": "EXPECTED",
        "dataSource": "incumbent",
        "isIncumbent": true,
        "_seats": 2,
        "pledges": []
      },
      {
        "name": "김항규",
        "party": "ppp",
        "career": "",
        "status": "EXPECTED",
        "dataSource": "incumbent",
        "isIncumbent": true,
        "_seats": 2,
        "pledges": []
      }
    ],
    "경주시나선거구": [
      {
        "name": "최영기",
        "party": "ppp",
        "career": "",
        "status": "EXPECTED",
        "dataSource": "incumbent",
        "isIncumbent": true,
        "_seats": 2,
        "pledges": []
      },
      {
        "name": "최재필",
        "party": "ppp",
        "career": "",
        "status": "EXPECTED",
        "dataSource": "incumbent",
        "isIncumbent": true,
        "_seats": 2,
        "pledges": []
      }
    ],
    "경주시다선거구": [
      {
        "name": "정종문",
        "party": "ppp",
        "career": "",
        "status": "EXPECTED",
        "dataSource": "incumbent",
        "isIncumbent": true,
        "_seats": 2,
        "pledges": []
      },
      {
        "name": "임활",
        "party": "ppp",
        "career": "",
        "status": "EXPECTED",
        "dataSource": "incumbent",
        "isIncumbent": true,
        "_seats": 2,
        "pledges": []
      }
    ],
    "경주시라선거구": [
      {
        "name": "주동열",
        "party": "ppp",
        "career": "",
        "status": "EXPECTED",
        "dataSource": "incumbent",
        "isIncumbent": true,
        "_seats": 3,
        "pledges": []
      },
      {
        "name": "오상도",
        "party": "independent",
        "career": "",
        "status": "EXPECTED",
        "dataSource": "incumbent",
        "isIncumbent": true,
        "_seats": 3,
        "pledges": []
      },
      {
        "name": "이진락",
        "party": "ppp",
        "career": "",
        "status": "EXPECTED",
        "dataSource": "incumbent",
        "isIncumbent": true,
        "_seats": 3,
        "pledges": []
      }
    ],
    "경주시마선거구": [
      {
        "name": "정성룡",
        "party": "ppp",
        "career": "",
        "status": "EXPECTED",
        "dataSource": "incumbent",
        "isIncumbent": true,
        "_seats": 2,
        "pledges": []
      },
      {
        "name": "이철우",
        "party": "ppp",
        "career": "",
        "status": "EXPECTED",
        "dataSource": "incumbent",
        "isIncumbent": true,
        "_seats": 2,
        "pledges": []
      }
    ],
    "경주시바선거구": [
      {
        "name": "정원기",
        "party": "ppp",
        "career": "",
        "status": "EXPECTED",
        "dataSource": "incumbent",
        "isIncumbent": true,
        "_seats": 2,
        "pledges": []
      },
      {
        "name": "이락우",
        "party": "ppp",
        "career": "",
        "status": "EXPECTED",
        "dataSource": "incumbent",
        "isIncumbent": true,
        "_seats": 2,
        "pledges": []
      }
    ],
    "경주시사선거구": [
      {
        "name": "김소현",
        "party": "ppp",
        "career": "",
        "status": "EXPECTED",
        "dataSource": "incumbent",
        "isIncumbent": true,
        "_seats": 3,
        "pledges": []
      },
      {
        "name": "박광호",
        "party": "ppp",
        "career": "",
        "status": "EXPECTED",
        "dataSource": "incumbent",
        "isIncumbent": true,
        "_seats": 3,
        "pledges": []
      },
      {
        "name": "김동해",
        "party": "independent",
        "career": "",
        "status": "EXPECTED",
        "dataSource": "incumbent",
        "isIncumbent": true,
        "_seats": 3,
        "pledges": []
      }
    ],
    "경주시아선거구": [
      {
        "name": "정희택",
        "party": "ppp",
        "career": "",
        "status": "EXPECTED",
        "dataSource": "incumbent",
        "isIncumbent": true,
        "_seats": 2,
        "pledges": []
      },
      {
        "name": "이동협",
        "party": "ppp",
        "career": "",
        "status": "EXPECTED",
        "dataSource": "incumbent",
        "isIncumbent": true,
        "_seats": 2,
        "pledges": []
      }
    ],
    "김천시가선거구": [
      {
        "name": "나영민",
        "party": "ppp",
        "career": "",
        "status": "EXPECTED",
        "dataSource": "incumbent",
        "isIncumbent": true,
        "_seats": 2,
        "pledges": []
      },
      {
        "name": "이복상",
        "party": "independent",
        "career": "",
        "status": "EXPECTED",
        "dataSource": "incumbent",
        "isIncumbent": true,
        "_seats": 2,
        "pledges": []
      }
    ],
    "김천시나선거구": [
      {
        "name": "이상욱",
        "party": "ppp",
        "career": "",
        "status": "EXPECTED",
        "dataSource": "incumbent",
        "isIncumbent": true,
        "_seats": 3,
        "pledges": []
      },
      {
        "name": "신세원",
        "party": "ppp",
        "career": "",
        "status": "EXPECTED",
        "dataSource": "incumbent",
        "isIncumbent": true,
        "_seats": 3,
        "pledges": []
      },
      {
        "name": "이명기",
        "party": "ppp",
        "career": "",
        "status": "EXPECTED",
        "dataSource": "incumbent",
        "isIncumbent": true,
        "_seats": 3,
        "pledges": []
      }
    ],
    "김천시다선거구": [
      {
        "name": "정재정",
        "party": "ppp",
        "career": "",
        "status": "EXPECTED",
        "dataSource": "incumbent",
        "isIncumbent": true,
        "_seats": 2,
        "pledges": []
      },
      {
        "name": "이승우",
        "party": "ppp",
        "career": "",
        "status": "EXPECTED",
        "dataSource": "incumbent",
        "isIncumbent": true,
        "_seats": 2,
        "pledges": []
      }
    ],
    "김천시라선거구": [
      {
        "name": "배형태",
        "party": "ppp",
        "career": "",
        "status": "EXPECTED",
        "dataSource": "incumbent",
        "isIncumbent": true,
        "_seats": 2,
        "pledges": []
      },
      {
        "name": "박대하",
        "party": "ppp",
        "career": "",
        "status": "EXPECTED",
        "dataSource": "incumbent",
        "isIncumbent": true,
        "_seats": 2,
        "pledges": []
      }
    ],
    "김천시마선거구": [
      {
        "name": "김세호",
        "party": "ppp",
        "career": "",
        "status": "EXPECTED",
        "dataSource": "incumbent",
        "isIncumbent": true,
        "_seats": 2,
        "pledges": []
      },
      {
        "name": "김석조",
        "party": "ppp",
        "career": "",
        "status": "EXPECTED",
        "dataSource": "incumbent",
        "isIncumbent": true,
        "_seats": 2,
        "pledges": []
      }
    ],
    "김천시바선거구": [
      {
        "name": "임동규",
        "party": "democratic",
        "career": "",
        "status": "EXPECTED",
        "dataSource": "incumbent",
        "isIncumbent": true,
        "_seats": 2,
        "pledges": []
      },
      {
        "name": "박근혜",
        "party": "ppp",
        "career": "",
        "status": "EXPECTED",
        "dataSource": "incumbent",
        "isIncumbent": true,
        "_seats": 2,
        "pledges": []
      }
    ],
    "김천시사선거구": [
      {
        "name": "오세길",
        "party": "ppp",
        "career": "",
        "status": "EXPECTED",
        "dataSource": "incumbent",
        "isIncumbent": true,
        "_seats": 3,
        "pledges": []
      },
      {
        "name": "윤영수",
        "party": "ppp",
        "career": "",
        "status": "EXPECTED",
        "dataSource": "incumbent",
        "isIncumbent": true,
        "_seats": 3,
        "pledges": []
      },
      {
        "name": "진기상",
        "party": "independent",
        "career": "",
        "status": "EXPECTED",
        "dataSource": "incumbent",
        "isIncumbent": true,
        "_seats": 3,
        "pledges": []
      }
    ],
    "안동시가선거구": [
      {
        "name": "우창하",
        "party": "ppp",
        "career": "",
        "status": "EXPECTED",
        "dataSource": "incumbent",
        "isIncumbent": true,
        "_seats": 2,
        "pledges": []
      },
      {
        "name": "김새롬",
        "party": "democratic",
        "career": "",
        "status": "EXPECTED",
        "dataSource": "incumbent",
        "isIncumbent": true,
        "_seats": 2,
        "pledges": []
      }
    ],
    "안동시나선거구": [
      {
        "name": "권기윤",
        "party": "ppp",
        "career": "",
        "status": "EXPECTED",
        "dataSource": "incumbent",
        "isIncumbent": true,
        "_seats": 2,
        "pledges": []
      },
      {
        "name": "정복순",
        "party": "democratic",
        "career": "",
        "status": "EXPECTED",
        "dataSource": "incumbent",
        "isIncumbent": true,
        "_seats": 2,
        "pledges": []
      }
    ],
    "안동시다선거구": [
      {
        "name": "김순중",
        "party": "democratic",
        "career": "",
        "status": "EXPECTED",
        "dataSource": "incumbent",
        "isIncumbent": true,
        "_seats": 2,
        "pledges": []
      },
      {
        "name": "권기탁",
        "party": "ppp",
        "career": "",
        "status": "EXPECTED",
        "dataSource": "incumbent",
        "isIncumbent": true,
        "_seats": 2,
        "pledges": []
      }
    ],
    "안동시라선거구": [
      {
        "name": "권기익",
        "party": "ppp",
        "career": "",
        "status": "EXPECTED",
        "dataSource": "incumbent",
        "isIncumbent": true,
        "_seats": 2,
        "pledges": []
      },
      {
        "name": "이재갑",
        "party": "independent",
        "career": "",
        "status": "EXPECTED",
        "dataSource": "incumbent",
        "isIncumbent": true,
        "_seats": 2,
        "pledges": []
      }
    ],
    "안동시마선거구": [
      {
        "name": "김창현",
        "party": "ppp",
        "career": "",
        "status": "EXPECTED",
        "dataSource": "incumbent",
        "isIncumbent": true,
        "_seats": 2,
        "pledges": []
      },
      {
        "name": "임태섭",
        "party": "independent",
        "career": "",
        "status": "EXPECTED",
        "dataSource": "incumbent",
        "isIncumbent": true,
        "_seats": 2,
        "pledges": []
      }
    ],
    "안동시바선거구": [
      {
        "name": "박치선",
        "party": "ppp",
        "career": "",
        "status": "EXPECTED",
        "dataSource": "incumbent",
        "isIncumbent": true,
        "_seats": 2,
        "pledges": []
      },
      {
        "name": "김호석",
        "party": "independent",
        "career": "",
        "status": "EXPECTED",
        "dataSource": "incumbent",
        "isIncumbent": true,
        "_seats": 2,
        "pledges": []
      }
    ],
    "안동시사선거구": [
      {
        "name": "안유안",
        "party": "ppp",
        "career": "",
        "status": "EXPECTED",
        "dataSource": "incumbent",
        "isIncumbent": true,
        "_seats": 2,
        "pledges": []
      },
      {
        "name": "손광영",
        "party": "independent",
        "career": "",
        "status": "EXPECTED",
        "dataSource": "incumbent",
        "isIncumbent": true,
        "_seats": 2,
        "pledges": []
      }
    ],
    "안동시아선거구": [
      {
        "name": "김경도",
        "party": "ppp",
        "career": "",
        "status": "EXPECTED",
        "dataSource": "incumbent",
        "isIncumbent": true,
        "_seats": 2,
        "pledges": []
      },
      {
        "name": "김상진",
        "party": "ppp",
        "career": "",
        "status": "EXPECTED",
        "dataSource": "incumbent",
        "isIncumbent": true,
        "_seats": 2,
        "pledges": []
      }
    ],
    "구미시가선거구": [
      {
        "name": "김민성",
        "party": "ppp",
        "career": "",
        "status": "EXPECTED",
        "dataSource": "incumbent",
        "isIncumbent": true,
        "_seats": 3,
        "pledges": []
      },
      {
        "name": "김재우",
        "party": "democratic",
        "career": "",
        "status": "EXPECTED",
        "dataSource": "incumbent",
        "isIncumbent": true,
        "_seats": 3,
        "pledges": []
      },
      {
        "name": "박교상",
        "party": "ppp",
        "career": "",
        "status": "EXPECTED",
        "dataSource": "incumbent",
        "isIncumbent": true,
        "_seats": 3,
        "pledges": []
      }
    ],
    "구미시나선거구": [
      {
        "name": "박세채",
        "party": "ppp",
        "career": "",
        "status": "EXPECTED",
        "dataSource": "incumbent",
        "isIncumbent": true,
        "_seats": 2,
        "pledges": []
      },
      {
        "name": "김낙관",
        "party": "ppp",
        "career": "",
        "status": "EXPECTED",
        "dataSource": "incumbent",
        "isIncumbent": true,
        "_seats": 2,
        "pledges": []
      }
    ],
    "구미시다선거구": [
      {
        "name": "김원섭",
        "party": "ppp",
        "career": "",
        "status": "EXPECTED",
        "dataSource": "incumbent",
        "isIncumbent": true,
        "_seats": 2,
        "pledges": []
      },
      {
        "name": "김영태",
        "party": "ppp",
        "career": "",
        "status": "EXPECTED",
        "dataSource": "incumbent",
        "isIncumbent": true,
        "_seats": 2,
        "pledges": []
      }
    ],
    "구미시라선거구": [
      {
        "name": "김정도",
        "party": "ppp",
        "career": "",
        "status": "EXPECTED",
        "dataSource": "incumbent",
        "isIncumbent": true,
        "_seats": 2,
        "pledges": []
      },
      {
        "name": "장세구",
        "party": "ppp",
        "career": "",
        "status": "EXPECTED",
        "dataSource": "incumbent",
        "isIncumbent": true,
        "_seats": 2,
        "pledges": []
      }
    ],
    "구미시마선거구": [
      {
        "name": "허민근",
        "party": "ppp",
        "career": "",
        "status": "EXPECTED",
        "dataSource": "incumbent",
        "isIncumbent": true,
        "_seats": 2,
        "pledges": []
      },
      {
        "name": "김춘남",
        "party": "ppp",
        "career": "",
        "status": "EXPECTED",
        "dataSource": "incumbent",
        "isIncumbent": true,
        "_seats": 2,
        "pledges": []
      }
    ],
    "구미시바선거구": [
      {
        "name": "장미경",
        "party": "ppp",
        "career": "",
        "status": "EXPECTED",
        "dataSource": "incumbent",
        "isIncumbent": true,
        "_seats": 2,
        "pledges": []
      },
      {
        "name": "양진오",
        "party": "ppp",
        "career": "",
        "status": "EXPECTED",
        "dataSource": "incumbent",
        "isIncumbent": true,
        "_seats": 2,
        "pledges": []
      }
    ],
    "구미시사선거구": [
      {
        "name": "이명희",
        "party": "ppp",
        "career": "",
        "status": "EXPECTED",
        "dataSource": "incumbent",
        "isIncumbent": true,
        "_seats": 2,
        "pledges": []
      },
      {
        "name": "강승수",
        "party": "ppp",
        "career": "",
        "status": "EXPECTED",
        "dataSource": "incumbent",
        "isIncumbent": true,
        "_seats": 2,
        "pledges": []
      }
    ],
    "구미시아선거구": [
      {
        "name": "신용하",
        "party": "democratic",
        "career": "",
        "status": "EXPECTED",
        "dataSource": "incumbent",
        "isIncumbent": true,
        "_seats": 2,
        "pledges": []
      },
      {
        "name": "김영길",
        "party": "ppp",
        "career": "",
        "status": "EXPECTED",
        "dataSource": "incumbent",
        "isIncumbent": true,
        "_seats": 2,
        "pledges": []
      }
    ],
    "구미시자선거구": [
      {
        "name": "이상호",
        "party": "democratic",
        "career": "",
        "status": "EXPECTED",
        "dataSource": "incumbent",
        "isIncumbent": true,
        "_seats": 3,
        "pledges": []
      },
      {
        "name": "소진혁",
        "party": "ppp",
        "career": "",
        "status": "EXPECTED",
        "dataSource": "incumbent",
        "isIncumbent": true,
        "_seats": 3,
        "pledges": []
      },
      {
        "name": "안주찬",
        "party": "ppp",
        "career": "",
        "status": "EXPECTED",
        "dataSource": "incumbent",
        "isIncumbent": true,
        "_seats": 3,
        "pledges": []
      }
    ],
    "구미시차선거구": [
      {
        "name": "정지원",
        "party": "ppp",
        "career": "",
        "status": "EXPECTED",
        "dataSource": "incumbent",
        "isIncumbent": true,
        "_seats": 2,
        "pledges": []
      },
      {
        "name": "이지연",
        "party": "democratic",
        "career": "",
        "status": "EXPECTED",
        "dataSource": "incumbent",
        "isIncumbent": true,
        "_seats": 2,
        "pledges": []
      }
    ],
    "영주시가선거구": [
      {
        "name": "이재원",
        "party": "ppp",
        "career": "",
        "status": "EXPECTED",
        "dataSource": "incumbent",
        "isIncumbent": true,
        "_seats": 2,
        "pledges": []
      },
      {
        "name": "김병기",
        "party": "ppp",
        "career": "",
        "status": "EXPECTED",
        "dataSource": "incumbent",
        "isIncumbent": true,
        "_seats": 2,
        "pledges": []
      }
    ],
    "영주시나선거구": [
      {
        "name": "유충상",
        "party": "ppp",
        "career": "",
        "status": "EXPECTED",
        "dataSource": "incumbent",
        "isIncumbent": true,
        "_seats": 2,
        "pledges": []
      },
      {
        "name": "심재연",
        "party": "ppp",
        "career": "",
        "status": "EXPECTED",
        "dataSource": "incumbent",
        "isIncumbent": true,
        "_seats": 2,
        "pledges": []
      }
    ],
    "영주시다선거구": [
      {
        "name": "김병창",
        "party": "ppp",
        "career": "",
        "status": "EXPECTED",
        "dataSource": "incumbent",
        "isIncumbent": true,
        "_seats": 2,
        "pledges": []
      },
      {
        "name": "우충무",
        "party": "independent",
        "career": "",
        "status": "EXPECTED",
        "dataSource": "incumbent",
        "isIncumbent": true,
        "_seats": 2,
        "pledges": []
      }
    ],
    "영주시라선거구": [
      {
        "name": "손성호",
        "party": "ppp",
        "career": "",
        "status": "EXPECTED",
        "dataSource": "incumbent",
        "isIncumbent": true,
        "_seats": 2,
        "pledges": []
      },
      {
        "name": "이상근",
        "party": "independent",
        "career": "",
        "status": "EXPECTED",
        "dataSource": "incumbent",
        "isIncumbent": true,
        "_seats": 2,
        "pledges": []
      }
    ],
    "영주시마선거구": [
      {
        "name": "전규호",
        "party": "ppp",
        "career": "",
        "status": "EXPECTED",
        "dataSource": "incumbent",
        "isIncumbent": true,
        "_seats": 2,
        "pledges": []
      },
      {
        "name": "김화숙",
        "party": "ppp",
        "career": "",
        "status": "EXPECTED",
        "dataSource": "incumbent",
        "isIncumbent": true,
        "_seats": 2,
        "pledges": []
      }
    ],
    "영주시바선거구": [
      {
        "name": "김주영",
        "party": "ppp",
        "career": "",
        "status": "EXPECTED",
        "dataSource": "incumbent",
        "isIncumbent": true,
        "_seats": 2,
        "pledges": []
      },
      {
        "name": "전풍림",
        "party": "independent",
        "career": "",
        "status": "EXPECTED",
        "dataSource": "incumbent",
        "isIncumbent": true,
        "_seats": 2,
        "pledges": []
      }
    ],
    "영천시가선거구": [
      {
        "name": "우애자",
        "party": "ppp",
        "career": "",
        "status": "EXPECTED",
        "dataSource": "incumbent",
        "isIncumbent": true,
        "_seats": 2,
        "pledges": []
      },
      {
        "name": "김선태",
        "party": "ppp",
        "career": "",
        "status": "EXPECTED",
        "dataSource": "incumbent",
        "isIncumbent": true,
        "_seats": 2,
        "pledges": []
      }
    ],
    "영천시나선거구": [
      {
        "name": "이영우",
        "party": "independent",
        "career": "",
        "status": "EXPECTED",
        "dataSource": "incumbent",
        "isIncumbent": true,
        "_seats": 3,
        "pledges": []
      },
      {
        "name": "김상호",
        "party": "ppp",
        "career": "",
        "status": "EXPECTED",
        "dataSource": "incumbent",
        "isIncumbent": true,
        "_seats": 3,
        "pledges": []
      },
      {
        "name": "김종욱",
        "party": "ppp",
        "career": "",
        "status": "EXPECTED",
        "dataSource": "incumbent",
        "isIncumbent": true,
        "_seats": 3,
        "pledges": []
      }
    ],
    "영천시다선거구": [
      {
        "name": "김용문",
        "party": "independent",
        "career": "",
        "status": "EXPECTED",
        "dataSource": "incumbent",
        "isIncumbent": true,
        "_seats": 3,
        "pledges": []
      },
      {
        "name": "하기태",
        "party": "ppp",
        "career": "",
        "status": "EXPECTED",
        "dataSource": "incumbent",
        "isIncumbent": true,
        "_seats": 3,
        "pledges": []
      },
      {
        "name": "이영기",
        "party": "ppp",
        "career": "",
        "status": "EXPECTED",
        "dataSource": "incumbent",
        "isIncumbent": true,
        "_seats": 3,
        "pledges": []
      }
    ],
    "영천시라선거구": [
      {
        "name": "권기한",
        "party": "ppp",
        "career": "",
        "status": "EXPECTED",
        "dataSource": "incumbent",
        "isIncumbent": true,
        "_seats": 2,
        "pledges": []
      },
      {
        "name": "이갑균",
        "party": "ppp",
        "career": "",
        "status": "EXPECTED",
        "dataSource": "incumbent",
        "isIncumbent": true,
        "_seats": 2,
        "pledges": []
      }
    ],
    "상주시가선거구": [
      {
        "name": "박광덕",
        "party": "ppp",
        "career": "",
        "status": "EXPECTED",
        "dataSource": "incumbent",
        "isIncumbent": true,
        "_seats": 2,
        "pledges": []
      },
      {
        "name": "한구홍",
        "party": "ppp",
        "career": "",
        "status": "EXPECTED",
        "dataSource": "incumbent",
        "isIncumbent": true,
        "_seats": 2,
        "pledges": []
      }
    ],
    "상주시나선거구": [
      {
        "name": "성성호",
        "party": "ppp",
        "career": "",
        "status": "EXPECTED",
        "dataSource": "incumbent",
        "isIncumbent": true,
        "_seats": 2,
        "pledges": []
      },
      {
        "name": "안창수",
        "party": "independent",
        "career": "",
        "status": "EXPECTED",
        "dataSource": "incumbent",
        "isIncumbent": true,
        "_seats": 2,
        "pledges": []
      }
    ],
    "상주시다선거구": [
      {
        "name": "김익상",
        "party": "ppp",
        "career": "",
        "status": "EXPECTED",
        "dataSource": "incumbent",
        "isIncumbent": true,
        "_seats": 3,
        "pledges": []
      },
      {
        "name": "이경옥",
        "party": "ppp",
        "career": "",
        "status": "EXPECTED",
        "dataSource": "incumbent",
        "isIncumbent": true,
        "_seats": 3,
        "pledges": []
      },
      {
        "name": "정길수",
        "party": "democratic",
        "career": "",
        "status": "EXPECTED",
        "dataSource": "incumbent",
        "isIncumbent": true,
        "_seats": 3,
        "pledges": []
      }
    ],
    "상주시라선거구": [
      {
        "name": "정석용",
        "party": "independent",
        "career": "",
        "status": "EXPECTED",
        "dataSource": "incumbent",
        "isIncumbent": true,
        "_seats": 2,
        "pledges": []
      },
      {
        "name": "박주형",
        "party": "ppp",
        "career": "",
        "status": "EXPECTED",
        "dataSource": "incumbent",
        "isIncumbent": true,
        "_seats": 2,
        "pledges": []
      }
    ],
    "상주시마선거구": [
      {
        "name": "진태종",
        "party": "ppp",
        "career": "",
        "status": "EXPECTED",
        "dataSource": "incumbent",
        "isIncumbent": true,
        "_seats": 3,
        "pledges": []
      },
      {
        "name": "강경모",
        "party": "ppp",
        "career": "",
        "status": "EXPECTED",
        "dataSource": "incumbent",
        "isIncumbent": true,
        "_seats": 3,
        "pledges": []
      },
      {
        "name": "신순화",
        "party": "ppp",
        "career": "",
        "status": "EXPECTED",
        "dataSource": "incumbent",
        "isIncumbent": true,
        "_seats": 3,
        "pledges": []
      }
    ],
    "상주시바선거구": [
      {
        "name": "김호",
        "party": "independent",
        "career": "",
        "status": "EXPECTED",
        "dataSource": "incumbent",
        "isIncumbent": true,
        "_seats": 3,
        "pledges": []
      },
      {
        "name": "강효구",
        "party": "ppp",
        "career": "",
        "status": "EXPECTED",
        "dataSource": "incumbent",
        "isIncumbent": true,
        "_seats": 3,
        "pledges": []
      },
      {
        "name": "안경숙",
        "party": "ppp",
        "career": "",
        "status": "EXPECTED",
        "dataSource": "incumbent",
        "isIncumbent": true,
        "_seats": 3,
        "pledges": []
      }
    ],
    "문경시가선거구": [
      {
        "name": "김경환",
        "party": "ppp",
        "career": "",
        "status": "EXPECTED",
        "dataSource": "incumbent",
        "isIncumbent": true,
        "_seats": 2,
        "pledges": []
      },
      {
        "name": "황재용",
        "party": "ppp",
        "career": "",
        "status": "EXPECTED",
        "dataSource": "incumbent",
        "isIncumbent": true,
        "_seats": 2,
        "pledges": []
      }
    ],
    "문경시나선거구": [
      {
        "name": "신성호",
        "party": "ppp",
        "career": "",
        "status": "EXPECTED",
        "dataSource": "incumbent",
        "isIncumbent": true,
        "_seats": 3,
        "pledges": []
      },
      {
        "name": "서정식",
        "party": "ppp",
        "career": "",
        "status": "EXPECTED",
        "dataSource": "incumbent",
        "isIncumbent": true,
        "_seats": 3,
        "pledges": []
      },
      {
        "name": "진후진",
        "party": "ppp",
        "career": "",
        "status": "EXPECTED",
        "dataSource": "incumbent",
        "isIncumbent": true,
        "_seats": 3,
        "pledges": []
      }
    ],
    "문경시다선거구": [
      {
        "name": "고상범",
        "party": "ppp",
        "career": "",
        "status": "EXPECTED",
        "dataSource": "incumbent",
        "isIncumbent": true,
        "_seats": 2,
        "pledges": []
      },
      {
        "name": "남기호",
        "party": "ppp",
        "career": "",
        "status": "EXPECTED",
        "dataSource": "incumbent",
        "isIncumbent": true,
        "_seats": 2,
        "pledges": []
      }
    ],
    "문경시라선거구": [
      {
        "name": "박춘남",
        "party": "ppp",
        "career": "",
        "status": "EXPECTED",
        "dataSource": "incumbent",
        "isIncumbent": true,
        "_seats": 2,
        "pledges": []
      },
      {
        "name": "이정걸",
        "party": "independent",
        "career": "",
        "status": "EXPECTED",
        "dataSource": "incumbent",
        "isIncumbent": true,
        "_seats": 2,
        "pledges": []
      }
    ],
    "예천군가선거구": [
      {
        "name": "장삼규",
        "party": "independent",
        "career": "",
        "status": "EXPECTED",
        "dataSource": "incumbent",
        "isIncumbent": true,
        "_seats": 2,
        "pledges": []
      },
      {
        "name": "신향순",
        "party": "ppp",
        "career": "",
        "status": "EXPECTED",
        "dataSource": "incumbent",
        "isIncumbent": true,
        "_seats": 2,
        "pledges": []
      }
    ],
    "예천군나선거구": [
      {
        "name": "김홍년",
        "party": "ppp",
        "career": "",
        "status": "EXPECTED",
        "dataSource": "incumbent",
        "isIncumbent": true,
        "_seats": 2,
        "pledges": []
      },
      {
        "name": "강영구",
        "party": "ppp",
        "career": "",
        "status": "EXPECTED",
        "dataSource": "incumbent",
        "isIncumbent": true,
        "_seats": 2,
        "pledges": []
      }
    ],
    "예천군다선거구": [
      {
        "name": "이동화",
        "party": "democratic",
        "career": "",
        "status": "EXPECTED",
        "dataSource": "incumbent",
        "isIncumbent": true,
        "_seats": 2,
        "pledges": []
      },
      {
        "name": "강경탁",
        "party": "ppp",
        "career": "",
        "status": "EXPECTED",
        "dataSource": "incumbent",
        "isIncumbent": true,
        "_seats": 2,
        "pledges": []
      }
    ],
    "예천군라선거구": [
      {
        "name": "박재길",
        "party": "ppp",
        "career": "",
        "status": "EXPECTED",
        "dataSource": "incumbent",
        "isIncumbent": true,
        "_seats": 2,
        "pledges": []
      },
      {
        "name": "최병욱",
        "party": "ppp",
        "career": "",
        "status": "EXPECTED",
        "dataSource": "incumbent",
        "isIncumbent": true,
        "_seats": 2,
        "pledges": []
      }
    ],
    "경산시가선거구": [
      {
        "name": "전봉근",
        "party": "ppp",
        "career": "",
        "status": "EXPECTED",
        "dataSource": "incumbent",
        "isIncumbent": true,
        "_seats": 3,
        "pledges": []
      },
      {
        "name": "김화선",
        "party": "ppp",
        "career": "",
        "status": "EXPECTED",
        "dataSource": "incumbent",
        "isIncumbent": true,
        "_seats": 3,
        "pledges": []
      },
      {
        "name": "김상호",
        "party": "ppp",
        "career": "",
        "status": "EXPECTED",
        "dataSource": "incumbent",
        "isIncumbent": true,
        "_seats": 3,
        "pledges": []
      }
    ],
    "경산시나선거구": [
      {
        "name": "이동욱",
        "party": "ppp",
        "career": "",
        "status": "EXPECTED",
        "dataSource": "incumbent",
        "isIncumbent": true,
        "_seats": 2,
        "pledges": []
      },
      {
        "name": "윤기현",
        "party": "ppp",
        "career": "",
        "status": "EXPECTED",
        "dataSource": "incumbent",
        "isIncumbent": true,
        "_seats": 2,
        "pledges": []
      }
    ],
    "경산시다선거구": [
      {
        "name": "박순득",
        "party": "ppp",
        "career": "",
        "status": "EXPECTED",
        "dataSource": "incumbent",
        "isIncumbent": true,
        "_seats": 2,
        "pledges": []
      },
      {
        "name": "강수명",
        "party": "independent",
        "career": "",
        "status": "EXPECTED",
        "dataSource": "incumbent",
        "isIncumbent": true,
        "_seats": 2,
        "pledges": []
      }
    ],
    "경산시라선거구": [
      {
        "name": "안문길",
        "party": "ppp",
        "career": "",
        "status": "EXPECTED",
        "dataSource": "incumbent",
        "isIncumbent": true,
        "_seats": 3,
        "pledges": []
      },
      {
        "name": "이경원",
        "party": "democratic",
        "career": "",
        "status": "EXPECTED",
        "dataSource": "incumbent",
        "isIncumbent": true,
        "_seats": 3,
        "pledges": []
      },
      {
        "name": "권중석",
        "party": "ppp",
        "career": "",
        "status": "EXPECTED",
        "dataSource": "incumbent",
        "isIncumbent": true,
        "_seats": 3,
        "pledges": []
      }
    ],
    "경산시마선거구": [
      {
        "name": "김인수",
        "party": "ppp",
        "career": "",
        "status": "EXPECTED",
        "dataSource": "incumbent",
        "isIncumbent": true,
        "_seats": 3,
        "pledges": []
      },
      {
        "name": "양재영",
        "party": "democratic",
        "career": "",
        "status": "EXPECTED",
        "dataSource": "incumbent",
        "isIncumbent": true,
        "_seats": 3,
        "pledges": []
      },
      {
        "name": "박미옥",
        "party": "ppp",
        "career": "",
        "status": "EXPECTED",
        "dataSource": "incumbent",
        "isIncumbent": true,
        "_seats": 3,
        "pledges": []
      }
    ],
    "청도군가선거구": [
      {
        "name": "김규봉",
        "party": "ppp",
        "career": "",
        "status": "EXPECTED",
        "dataSource": "incumbent",
        "isIncumbent": true,
        "_seats": 3,
        "pledges": []
      },
      {
        "name": "이승민",
        "party": "independent",
        "career": "",
        "status": "EXPECTED",
        "dataSource": "incumbent",
        "isIncumbent": true,
        "_seats": 3,
        "pledges": []
      },
      {
        "name": "전종율",
        "party": "ppp",
        "career": "",
        "status": "EXPECTED",
        "dataSource": "incumbent",
        "isIncumbent": true,
        "_seats": 3,
        "pledges": []
      }
    ],
    "청도군나선거구": [
      {
        "name": "박성곤",
        "party": "ppp",
        "career": "",
        "status": "EXPECTED",
        "dataSource": "incumbent",
        "isIncumbent": true,
        "_seats": 3,
        "pledges": []
      },
      {
        "name": "김효태",
        "party": "ppp",
        "career": "",
        "status": "EXPECTED",
        "dataSource": "incumbent",
        "isIncumbent": true,
        "_seats": 3,
        "pledges": []
      },
      {
        "name": "김태이",
        "party": "ppp",
        "career": "",
        "status": "EXPECTED",
        "dataSource": "incumbent",
        "isIncumbent": true,
        "_seats": 3,
        "pledges": []
      }
    ],
    "고령군가선거구": [
      {
        "name": "김기창",
        "party": "ppp",
        "career": "",
        "status": "EXPECTED",
        "dataSource": "incumbent",
        "isIncumbent": true,
        "_seats": 2,
        "pledges": []
      },
      {
        "name": "성원환",
        "party": "ppp",
        "career": "",
        "status": "EXPECTED",
        "dataSource": "incumbent",
        "isIncumbent": true,
        "_seats": 2,
        "pledges": []
      }
    ],
    "고령군나선거구": [
      {
        "name": "성낙철",
        "party": "ppp",
        "career": "",
        "status": "EXPECTED",
        "dataSource": "incumbent",
        "isIncumbent": true,
        "_seats": 2,
        "pledges": []
      },
      {
        "name": "이달호",
        "party": "ppp",
        "career": "",
        "status": "EXPECTED",
        "dataSource": "incumbent",
        "isIncumbent": true,
        "_seats": 2,
        "pledges": []
      }
    ],
    "고령군다선거구": [
      {
        "name": "김명국",
        "party": "ppp",
        "career": "",
        "status": "EXPECTED",
        "dataSource": "incumbent",
        "isIncumbent": true,
        "_seats": 2,
        "pledges": []
      },
      {
        "name": "이철호",
        "party": "independent",
        "career": "",
        "status": "EXPECTED",
        "dataSource": "incumbent",
        "isIncumbent": true,
        "_seats": 2,
        "pledges": []
      }
    ],
    "성주군가선거구": [
      {
        "name": "도희재",
        "party": "ppp",
        "career": "",
        "status": "EXPECTED",
        "dataSource": "incumbent",
        "isIncumbent": true,
        "_seats": 3,
        "pledges": []
      },
      {
        "name": "김성우",
        "party": "ppp",
        "career": "",
        "status": "EXPECTED",
        "dataSource": "incumbent",
        "isIncumbent": true,
        "_seats": 3,
        "pledges": []
      },
      {
        "name": "김경호",
        "party": "ppp",
        "career": "",
        "status": "EXPECTED",
        "dataSource": "incumbent",
        "isIncumbent": true,
        "_seats": 3,
        "pledges": []
      }
    ],
    "성주군나선거구": [
      {
        "name": "장익봉",
        "party": "ppp",
        "career": "",
        "status": "EXPECTED",
        "dataSource": "incumbent",
        "isIncumbent": true,
        "_seats": 2,
        "pledges": []
      },
      {
        "name": "김종식",
        "party": "ppp",
        "career": "",
        "status": "EXPECTED",
        "dataSource": "incumbent",
        "isIncumbent": true,
        "_seats": 2,
        "pledges": []
      }
    ],
    "성주군다선거구": [
      {
        "name": "여노연",
        "party": "independent",
        "career": "",
        "status": "EXPECTED",
        "dataSource": "incumbent",
        "isIncumbent": true,
        "_seats": 2,
        "pledges": []
      },
      {
        "name": "구교강",
        "party": "ppp",
        "career": "",
        "status": "EXPECTED",
        "dataSource": "incumbent",
        "isIncumbent": true,
        "_seats": 2,
        "pledges": []
      }
    ],
    "칠곡군가선거구": [
      {
        "name": "배성도",
        "party": "ppp",
        "career": "",
        "status": "EXPECTED",
        "dataSource": "incumbent",
        "isIncumbent": true,
        "_seats": 2,
        "pledges": []
      },
      {
        "name": "권선호",
        "party": "ppp",
        "career": "",
        "status": "EXPECTED",
        "dataSource": "incumbent",
        "isIncumbent": true,
        "_seats": 2,
        "pledges": []
      }
    ],
    "칠곡군나선거구": [
      {
        "name": "오종열",
        "party": "ppp",
        "career": "",
        "status": "EXPECTED",
        "dataSource": "incumbent",
        "isIncumbent": true,
        "_seats": 2,
        "pledges": []
      },
      {
        "name": "이상승",
        "party": "ppp",
        "career": "",
        "status": "EXPECTED",
        "dataSource": "incumbent",
        "isIncumbent": true,
        "_seats": 2,
        "pledges": []
      }
    ],
    "칠곡군다선거구": [
      {
        "name": "김태희",
        "party": "ppp",
        "career": "",
        "status": "EXPECTED",
        "dataSource": "incumbent",
        "isIncumbent": true,
        "_seats": 3,
        "pledges": []
      },
      {
        "name": "오용만",
        "party": "ppp",
        "career": "",
        "status": "EXPECTED",
        "dataSource": "incumbent",
        "isIncumbent": true,
        "_seats": 3,
        "pledges": []
      },
      {
        "name": "이창훈",
        "party": "democratic",
        "career": "",
        "status": "EXPECTED",
        "dataSource": "incumbent",
        "isIncumbent": true,
        "_seats": 3,
        "pledges": []
      }
    ],
    "칠곡군라선거구": [
      {
        "name": "심청보",
        "party": "ppp",
        "career": "",
        "status": "EXPECTED",
        "dataSource": "incumbent",
        "isIncumbent": true,
        "_seats": 2,
        "pledges": []
      },
      {
        "name": "구정회",
        "party": "democratic",
        "career": "",
        "status": "EXPECTED",
        "dataSource": "incumbent",
        "isIncumbent": true,
        "_seats": 2,
        "pledges": []
      }
    ],
    "군위군가선거구": [
      {
        "name": "서대식",
        "party": "ppp",
        "career": "",
        "status": "EXPECTED",
        "dataSource": "incumbent",
        "isIncumbent": true,
        "_seats": 3,
        "pledges": []
      },
      {
        "name": "박운표",
        "party": "independent",
        "career": "",
        "status": "EXPECTED",
        "dataSource": "incumbent",
        "isIncumbent": true,
        "_seats": 3,
        "pledges": []
      },
      {
        "name": "홍복순",
        "party": "independent",
        "career": "",
        "status": "EXPECTED",
        "dataSource": "incumbent",
        "isIncumbent": true,
        "_seats": 3,
        "pledges": []
      }
    ],
    "군위군나선거구": [
      {
        "name": "장철식",
        "party": "ppp",
        "career": "",
        "status": "EXPECTED",
        "dataSource": "incumbent",
        "isIncumbent": true,
        "_seats": 3,
        "pledges": []
      },
      {
        "name": "최규종",
        "party": "ppp",
        "career": "",
        "status": "EXPECTED",
        "dataSource": "incumbent",
        "isIncumbent": true,
        "_seats": 3,
        "pledges": []
      },
      {
        "name": "박수현",
        "party": "ppp",
        "career": "",
        "status": "EXPECTED",
        "dataSource": "incumbent",
        "isIncumbent": true,
        "_seats": 3,
        "pledges": []
      }
    ],
    "의성군가선거구": [
      {
        "name": "지무진",
        "party": "ppp",
        "career": "",
        "status": "EXPECTED",
        "dataSource": "incumbent",
        "isIncumbent": true,
        "_seats": 3,
        "pledges": []
      },
      {
        "name": "김현찬",
        "party": "ppp",
        "career": "",
        "status": "EXPECTED",
        "dataSource": "incumbent",
        "isIncumbent": true,
        "_seats": 3,
        "pledges": []
      },
      {
        "name": "황무용",
        "party": "ppp",
        "career": "",
        "status": "EXPECTED",
        "dataSource": "incumbent",
        "isIncumbent": true,
        "_seats": 3,
        "pledges": []
      }
    ],
    "의성군나선거구": [
      {
        "name": "배재봉",
        "party": "ppp",
        "career": "",
        "status": "EXPECTED",
        "dataSource": "incumbent",
        "isIncumbent": true,
        "_seats": 2,
        "pledges": []
      },
      {
        "name": "김광호",
        "party": "ppp",
        "career": "",
        "status": "EXPECTED",
        "dataSource": "incumbent",
        "isIncumbent": true,
        "_seats": 2,
        "pledges": []
      }
    ],
    "의성군다선거구": [
      {
        "name": "오호열",
        "party": "ppp",
        "career": "",
        "status": "EXPECTED",
        "dataSource": "incumbent",
        "isIncumbent": true,
        "_seats": 2,
        "pledges": []
      },
      {
        "name": "김동준",
        "party": "independent",
        "career": "",
        "status": "EXPECTED",
        "dataSource": "incumbent",
        "isIncumbent": true,
        "_seats": 2,
        "pledges": []
      }
    ],
    "의성군라선거구": [
      {
        "name": "김민주",
        "party": "independent",
        "career": "",
        "status": "EXPECTED",
        "dataSource": "incumbent",
        "isIncumbent": true,
        "_seats": 2,
        "pledges": []
      },
      {
        "name": "박화자",
        "party": "ppp",
        "career": "",
        "status": "EXPECTED",
        "dataSource": "incumbent",
        "isIncumbent": true,
        "_seats": 2,
        "pledges": []
      }
    ],
    "의성군마선거구": [
      {
        "name": "우칠윤",
        "party": "ppp",
        "career": "",
        "status": "EXPECTED",
        "dataSource": "incumbent",
        "isIncumbent": true,
        "_seats": 2,
        "pledges": []
      },
      {
        "name": "최훈식",
        "party": "ppp",
        "career": "",
        "status": "EXPECTED",
        "dataSource": "incumbent",
        "isIncumbent": true,
        "_seats": 2,
        "pledges": []
      }
    ],
    "청송군가선거구": [
      {
        "name": "조찬걸",
        "party": "ppp",
        "career": "",
        "status": "EXPECTED",
        "dataSource": "incumbent",
        "isIncumbent": true,
        "_seats": 3,
        "pledges": []
      },
      {
        "name": "황진수",
        "party": "ppp",
        "career": "",
        "status": "EXPECTED",
        "dataSource": "incumbent",
        "isIncumbent": true,
        "_seats": 3,
        "pledges": []
      },
      {
        "name": "심상휴",
        "party": "ppp",
        "career": "",
        "status": "EXPECTED",
        "dataSource": "incumbent",
        "isIncumbent": true,
        "_seats": 3,
        "pledges": []
      }
    ],
    "청송군나선거구": [
      {
        "name": "윤영경",
        "party": "ppp",
        "career": "",
        "status": "EXPECTED",
        "dataSource": "incumbent",
        "isIncumbent": true,
        "_seats": 3,
        "pledges": []
      },
      {
        "name": "권태준",
        "party": "ppp",
        "career": "",
        "status": "EXPECTED",
        "dataSource": "incumbent",
        "isIncumbent": true,
        "_seats": 3,
        "pledges": []
      },
      {
        "name": "정미진",
        "party": "ppp",
        "career": "",
        "status": "EXPECTED",
        "dataSource": "incumbent",
        "isIncumbent": true,
        "_seats": 3,
        "pledges": []
      }
    ],
    "영양군가선거구": [
      {
        "name": "우승원",
        "party": "ppp",
        "career": "",
        "status": "EXPECTED",
        "dataSource": "incumbent",
        "isIncumbent": true,
        "_seats": 3,
        "pledges": []
      },
      {
        "name": "김영범",
        "party": "ppp",
        "career": "",
        "status": "EXPECTED",
        "dataSource": "incumbent",
        "isIncumbent": true,
        "_seats": 3,
        "pledges": []
      },
      {
        "name": "장영호",
        "party": "democratic",
        "career": "",
        "status": "EXPECTED",
        "dataSource": "incumbent",
        "isIncumbent": true,
        "_seats": 3,
        "pledges": []
      }
    ],
    "영양군나선거구": [
      {
        "name": "장수상",
        "party": "ppp",
        "career": "",
        "status": "EXPECTED",
        "dataSource": "incumbent",
        "isIncumbent": true,
        "_seats": 3,
        "pledges": []
      },
      {
        "name": "홍점표",
        "party": "ppp",
        "career": "",
        "status": "EXPECTED",
        "dataSource": "incumbent",
        "isIncumbent": true,
        "_seats": 3,
        "pledges": []
      },
      {
        "name": "김석현",
        "party": "ppp",
        "career": "",
        "status": "EXPECTED",
        "dataSource": "incumbent",
        "isIncumbent": true,
        "_seats": 3,
        "pledges": []
      }
    ],
    "영덕군가선거구": [
      {
        "name": "배재현",
        "party": "ppp",
        "career": "",
        "status": "EXPECTED",
        "dataSource": "incumbent",
        "isIncumbent": true,
        "_seats": 3,
        "pledges": []
      },
      {
        "name": "김성철",
        "party": "ppp",
        "career": "",
        "status": "EXPECTED",
        "dataSource": "incumbent",
        "isIncumbent": true,
        "_seats": 3,
        "pledges": []
      },
      {
        "name": "김은희",
        "party": "ppp",
        "career": "",
        "status": "EXPECTED",
        "dataSource": "incumbent",
        "isIncumbent": true,
        "_seats": 3,
        "pledges": []
      }
    ],
    "영덕군나선거구": [
      {
        "name": "손덕수",
        "party": "ppp",
        "career": "",
        "status": "EXPECTED",
        "dataSource": "incumbent",
        "isIncumbent": true,
        "_seats": 3,
        "pledges": []
      },
      {
        "name": "김성호",
        "party": "independent",
        "career": "",
        "status": "EXPECTED",
        "dataSource": "incumbent",
        "isIncumbent": true,
        "_seats": 3,
        "pledges": []
      },
      {
        "name": "김일규",
        "party": "ppp",
        "career": "",
        "status": "EXPECTED",
        "dataSource": "incumbent",
        "isIncumbent": true,
        "_seats": 3,
        "pledges": []
      }
    ],
    "봉화군가선거구": [
      {
        "name": "이승훈",
        "party": "ppp",
        "career": "",
        "status": "EXPECTED",
        "dataSource": "incumbent",
        "isIncumbent": true,
        "_seats": 2,
        "pledges": []
      },
      {
        "name": "김상희",
        "party": "ppp",
        "career": "",
        "status": "EXPECTED",
        "dataSource": "incumbent",
        "isIncumbent": true,
        "_seats": 2,
        "pledges": []
      }
    ],
    "봉화군나선거구": [
      {
        "name": "금동윤",
        "party": "ppp",
        "career": "",
        "status": "EXPECTED",
        "dataSource": "incumbent",
        "isIncumbent": true,
        "_seats": 2,
        "pledges": []
      },
      {
        "name": "박동교",
        "party": "ppp",
        "career": "",
        "status": "EXPECTED",
        "dataSource": "incumbent",
        "isIncumbent": true,
        "_seats": 2,
        "pledges": []
      }
    ],
    "봉화군다선거구": [
      {
        "name": "김민호",
        "party": "ppp",
        "career": "",
        "status": "EXPECTED",
        "dataSource": "incumbent",
        "isIncumbent": true,
        "_seats": 3,
        "pledges": []
      },
      {
        "name": "황문익",
        "party": "independent",
        "career": "",
        "status": "EXPECTED",
        "dataSource": "incumbent",
        "isIncumbent": true,
        "_seats": 3,
        "pledges": []
      },
      {
        "name": "권영준",
        "party": "ppp",
        "career": "",
        "status": "EXPECTED",
        "dataSource": "incumbent",
        "isIncumbent": true,
        "_seats": 3,
        "pledges": []
      }
    ],
    "울진군가선거구": [
      {
        "name": "박영길",
        "party": "independent",
        "career": "",
        "status": "EXPECTED",
        "dataSource": "incumbent",
        "isIncumbent": true,
        "_seats": 2,
        "pledges": []
      },
      {
        "name": "임승필",
        "party": "ppp",
        "career": "",
        "status": "EXPECTED",
        "dataSource": "incumbent",
        "isIncumbent": true,
        "_seats": 2,
        "pledges": []
      }
    ],
    "울진군나선거구": [
      {
        "name": "임동인",
        "party": "ppp",
        "career": "",
        "status": "EXPECTED",
        "dataSource": "incumbent",
        "isIncumbent": true,
        "_seats": 2,
        "pledges": []
      },
      {
        "name": "장유덕",
        "party": "independent",
        "career": "",
        "status": "EXPECTED",
        "dataSource": "incumbent",
        "isIncumbent": true,
        "_seats": 2,
        "pledges": []
      }
    ],
    "울진군다선거구": [
      {
        "name": "황현철",
        "party": "ppp",
        "career": "",
        "status": "EXPECTED",
        "dataSource": "incumbent",
        "isIncumbent": true,
        "_seats": 3,
        "pledges": []
      },
      {
        "name": "안순자",
        "party": "independent",
        "career": "",
        "status": "EXPECTED",
        "dataSource": "incumbent",
        "isIncumbent": true,
        "_seats": 3,
        "pledges": []
      },
      {
        "name": "김정희",
        "party": "ppp",
        "career": "",
        "status": "EXPECTED",
        "dataSource": "incumbent",
        "isIncumbent": true,
        "_seats": 3,
        "pledges": []
      }
    ]
  }
}
